pinp/__init__.py
pinp-0.0.0.dist-info/METADATA
pinp-0.0.0.dist-info/WHEEL
pinp-0.0.0.dist-info/top_level.txt
pinp-0.0.0.dist-info/RECORD
