Metadata-Version: 2.1
Name: pinp
Version: 0.0.0
Summary: Coming soon
Author-email: TAILSIT <info@tailsit.com>
